redact_dotenv/__init__.py
redact_dotenv/cli.py
redact_dotenv-1.0.2.dist-info/licenses/LICENSE
redact_dotenv-1.0.2.dist-info/METADATA
redact_dotenv-1.0.2.dist-info/WHEEL
redact_dotenv-1.0.2.dist-info/entry_points.txt
redact_dotenv-1.0.2.dist-info/top_level.txt
redact_dotenv-1.0.2.dist-info/RECORD
