Metadata-Version: 2.4
Name: redact-dotenv
Version: 1.0.2
Summary: CLI tool to redact secrets from .env files
Author-email: Etienne Bourgeois <etienne@hanstechnologies.ca>
License: GPL-3.0
Requires-Python: >=3.7
License-File: LICENSE
Requires-Dist: click>=8.0
Dynamic: license-file
